html_utils/CSS.py
html_utils/HTML.py
html_utils/__init__.py
html_utils/filemodel.py
html_utils_becothal-1.3.dist-info/LICENSE
html_utils_becothal-1.3.dist-info/METADATA
html_utils_becothal-1.3.dist-info/WHEEL
html_utils_becothal-1.3.dist-info/top_level.txt
html_utils_becothal-1.3.dist-info/RECORD
