Metadata-Version: 2.1
Name: html-utils-becothal
Version: 1.3
Summary: A tool to inline CSS files into HTML.
Home-page: https://gitlab.com/ljedinger/html_utils
Author: Lukas Jedinger
Author-email: lukas.jedinger@gmail.com
License: UNKNOWN
Platform: UNKNOWN
